{
  "ഇഞ്ചി": {
    "നാമം": "ഇഞ്ചി",
    "ജൈവ നാമം": "സിംഗിബർ ഒഫിസിനാലെ",
    "വിവരണം": "ഇഞ്ചി ഒരു പുഷ്പിക്കുന്ന ചെടിയാണ്, ഇഞ്ചി സുഗന്ധവ്യഞ്ജനമായും ഔഷധമായും വ്യാപകമായി ഉപയോഗിക്കുന്നു",
    "ഉപയോഗങ്ങൾ": [
      "മോണിംഗ്സിക്ക്നസ്",
      "മോഷൻ സിക്ക്നസ്",
      "ഓക്കാനം",
      "ഛർദ്ദി"
    ],
    "പ്രയോജനങ്ങൾ": [
      "ആൻറി-ഇൻഫ്ലമേറ്ററി",
      "ആൻ്റിഓക്‌സിഡൻ്റ് ഇഫക്റ്റുകൾ ഉണ്ട്",
      "പേശി വേദന കുറയ്ക്കും",
      "രക്തത്തിലെ പഞ്ചസാരയുടെ അളവ് കുറയ്ക്കുകയും ഹൃദ്രോഗ സാധ്യത കുറയ്ക്കുകയും"
    ],
    "പാർശ്വഫലങ്ങൾ": [
      "നെഞ്ചെരിച്ചിൽ",
      "വയറിളക്കം",
      "വയറ്റിലെ അസ്വസ്ഥത"
    ],
    "സുരക്ഷ മുന്നറിയിപ്പുകൾ": "മിക്ക ആളുകൾക്കും ഇത് സുരക്ഷിതമാണെന്ന് പൊതുവെ കണക്കാക്കപ്പെടുന്നു, എന്നാൽ വലിയ അളവിലായാൽ നെഞ്ചെരിച്ചിലും മറ്റ് ദഹനസംബന്ധമായ പ്രശ്നങ്ങൾക്കും കാരണമായേക്കാം. ഗർഭിണികൾ ഇഞ്ചി ഉപയോഗിക്കുന്നതിന് മുമ്പ് ഡോക്ടറെ സമീപിക്കണം",
    "മരുന്ന് അലർജികൾ": "രക്തം നേർപ്പിക്കുന്നതും പ്രമേഹ മരുന്നുകളും ഉൾപ്പെടെയുള്ള ചില മരുന്നുകൾ ഉപയോഗിക്കുന്നവർ ഇത് ഒഴിവാക്കുക"
  },
  "കറ്റാർ വാഴ": {
    "നാമം": "കറ്റാർ വാഴ",
    "ജൈവ നാമം": "അലോ ബാർബഡെൻസിസ് മില്ലർ",
    "വിവരണം": "അസ്ഫോഡെലേസിയേ കുടുംബത്തിൽ പെടുന്ന ഒരു സസ്യ ഇനമാണ് കറ്റാർ വാഴ. അറേബ്യൻ പെനിൻസുലയിൽ നിന്നുള്ളതാണ്, പക്ഷേ ഔഷധമൂല്യവും അലങ്കാരമൂല്യവും കണക്കിലെടുത്ത് ലോകമെമ്പാടും ഇത് കൃഷിചെയ്യുന്നു.",
    "ഉപയോഗങ്ങൾ": [
      "കറ്റാർ വാഴ ജെൽ സൗന്ദര്യവർദ്ധക വസ്തുക്കളിലും",
      "ചർമ്മ സംരക്ഷണ ഉൽപ്പന്നങ്ങളിലും",
      "പരമ്പരാഗത വൈദ്യശാസ്ത്രത്തിലും ഉപയോഗിക്കുന്നു"
    ],
    "പ്രയോജനങ്ങൾ": [
      "കറ്റാർ വാഴ ജെൽ അതിൻ്റെ മോയ്സ്ചറൈസിംഗ്, രോഗശാന്തി ഗുണങ്ങൾക്ക് പേരുകേട്ടതാണ്",
      "സൂര്യതാപം, ചർമ്മത്തിലെ പ്രകോപനം, മുറിവുകൾ, മുഖക്കുരു, ദഹന പ്രശ്നങ്ങൾ എന്നിവ ചികിത്സിക്കാൻ ഇത് ഉപയോഗിക്കുന്നു"
    ],
    "പാർശ്വഫലങ്ങൾ": [
      "അലർജി",
      "ചർമ്മ പ്രകോപനം",
      "ദഹനനാളത്തിൻ്റെ അസ്വസ്ഥത"
    ],
    "സുരക്ഷ മുന്നറിയിപ്പുകൾ": "കറ്റാർ വാഴ ജെൽ പൊതുവെ സുരക്ഷിതമാണ്, എന്നാൽ സെൻസിറ്റീവ് ചർമ്മമോ അലർജിയോ ഉള്ള വ്യക്തികൾ ഉപയോഗിക്കുന്നതിന് മുമ്പ് ഒരു പാച്ച് ടെസ്റ്റ് നടത്തണം. കറ്റാർ വാഴ ലാറ്റക്സ് ജാഗ്രതയോടെയും ഒരു ഹെൽത്ത് കെയർ പ്രൊഫഷണലിൻ്റെ മാർഗ്ഗനിർദ്ദേശത്തിലും ഉപയോഗിക്കേണ്ടതാണ്",
    "മരുന്ന് അലർജികൾ": "കറ്റാർ വാഴയുമായി ബന്ധപ്പെട്ട പ്രത്യേക അലർജികൾ ഒന്നുമില്ല, എന്നാൽ അസ്ഫോഡെലേസി കുടുംബത്തിലെ സസ്യങ്ങളോട് അലർജിയുള്ള വ്യക്തികൾ ജാഗ്രത പാലിക്കണം"
  },
  "നെല്ലിക്ക": {
    "നാമം": "നെല്ലിക്ക",
    "ജൈവ നാമം": "ഫില്ലതുസ് എംബ്ലിക",
    "വിവരണം": "ഇന്ത്യൻ നെല്ലിക്ക എന്ന് അറിയപ്പെടുന്ന അംല, ഫില്ലന്തഷ്യ കുടുംബത്തിൽപ്പെട്ട ഒരു ചെറിയ ഇലപൊഴിയും വൃക്ഷമാണ്. ഇത് ഇന്ത്യൻ ഉപഭൂഖണ്ഡത്തിൽ നിന്നുള്ളതാണ്, എന്നാൽ മറ്റ് ഉഷ്ണമേഖലാ പ്രദേശങ്ങളിലും കാണപ്പെടുന്നു. ഭക്ഷ്യയോഗ്യമായ പഴങ്ങൾക്ക് പേരുകേട്ടതാണ് നെല്ലിക്ക. ഇത് പാചക വിഭവം, ഔഷധസസ്യം  എന്നിവയായി ഉപയോഗിക്കുന്നു.",
    "ഉപയോഗങ്ങൾ": [
      "നെല്ലിക്ക പാനീയങ്ങൾ",
      "ഹെർബൽ ടീ"
    ],
    "പ്രയോജനങ്ങൾ": [
      "ആൻറി ഓക്സിഡൻറ്",
      "ആൻറി-ഇൻഫ്ലമേറ്ററി",
      "പ്രതിരോധശേഷി വർധിപ്പിക്കുന്ന ഫലങ്ങളുള്ള വിറ്റാമിൻ സി, ടാന്നിൻസ്, ഫ്ലേവനോയ്ഡുകൾ തുടങ്ങിയ ബയോആക്ടീവ് സംയുക്തങ്ങൾ"
    ],
    "പാർശ്വഫലങ്ങൾ": [
      "അലർജി",
      "ദഹനനാളത്തിൻ്റെ അസ്വസ്ഥത"
    ],
    "സുരക്ഷ മുന്നറിയിപ്പുകൾ": "ഗർഭിണികൾ, മുലയൂട്ടുന്ന അമ്മമാർ, അലർജിയോ ദഹനസംബന്ധമായ പ്രശ്‌നങ്ങളോ ഉള്ള വ്യക്തികൾ നെല്ലിക്ക ഉപയോഗിക്കേണ്ടത് ഒരു ഹെൽത്ത് കെയർ പ്രൊഫഷണലിൻറെ നേതൃത്വത്തിലാണ്.",
    "മരുന്ന് അലർജികൾ": "നെല്ലിക്കയുമായി ബന്ധപ്പെട്ട പ്രത്യേക മരുന്ന് അലർജികൾ ഒന്നുമില്ല"
  },
  "ബ്രഹ്മി": {
    "നാമം": "ബ്രഹ്മി",
    "ജൈവ നാമം": "ബാകോപാ മൊന്നിയറി",
    "വിവരണം": "ബാകോപാ മൊന്നിയറി എന്നു അറിയപ്പെടുന്ന ബ്രഹ്മി പ്ലൻ്റാഗിനഷ്യ കുടുംബത്തിൽ പെട്ട ഒരു സസ്യമാണ്. ദക്ഷിണേഷ്യ, യൂറോപ്പ്, ആഫ്രിക്ക, വടക്കേ അമേരിക്ക എന്നിവിടങ്ങളിലെ തണ്ണീർത്തടങ്ങളും ചതുപ്പുനിലങ്ങളും ആണ് ഇതിൻ്റെ ജന്മദേശം. ബ്രഹ്മി നൂറ്റാണ്ടുകളായി ഒരു ഔഷധസസ്യമായി ഉപയോഗിക്കുന്നു.",
    "ഉപയോഗങ്ങൾ": [
      "ബ്രഹ്മി പരമ്പരാഗത വൈദ്യശാസ്ത്രത്തിൽ ഓർമ്മശക്തി",
      "മാനസിക വ്യക്തത",
      "ഉത്കണ്ഠ",
      "വിഷാദം",
      "സമ്മർദ്ദം",
      "നാഡീസംബന്ധമായ തകരാറുകൾ"
    ],
    "പ്രയോജനങ്ങൾ": [
      "ന്യൂറോപ്രൊട്ടക്റ്റീവ്",
      "ആൻ്റിഓക്‌സിഡൻറ്",
      "അഡാപ്റ്റോജെനിക് ഇഫക്റ്റുകൾ",
      "ആൽക്കലോയിഡുകൾ",
      "ഫ്ലേവനോയ്ഡുകൾ"
    ],
    "പാർശ്വഫലങ്ങൾ": [
      "ദഹനനാളത്തിൻ്റെ അസ്വസ്ഥത",
      "ഓക്കാനം",
      "അലർജി"
    ],
    "സുരക്ഷ മുന്നറിയിപ്പുകൾ": "ഗർഭിണികൾ, മുലയൂട്ടുന്ന അമ്മമാർ, അലർജിയോ ന്യൂറോളജിക്കൽ ഡിസോർഡേഴ്സ് ഉള്ള വ്യക്തികൾ ഒരു ഹെൽത്ത് കെയർ പ്രൊഫഷണലിൻറെ മാർഗ്ഗനിർദ്ദേശത്തിൽ ബ്രഹ്മി ഉപയോഗിക്കണം.",
    "മരുന്ന് അലർജികൾ": "ബ്രഹ്മിയുമായി ബന്ധപ്പെട്ട പ്രത്യേക അലർജികൾ ഒന്നുമില്ല"
  },
  "വേപ്പ്": {
    "നാമം": "വേപ്പ്",
    "ജൈവ നാമം": "അസാദിരാച്ച ഇൻഡിക്ക",
    "വിവരണം": "വേപ്പ് മെലിയേസി കുടുംബത്തിൽ പെടുന്ന ഒരു നിത്യഹരിത വൃക്ഷമാണ്. ഇത് ഇന്ത്യൻ ഉപഭൂഖണ്ഡത്തിൽ നിന്നുള്ളതാണ്, ഇത് ലോകമെമ്പാടുമുള്ള ഉഷ്ണമേഖലാ പ്രദേശങ്ങളിൽ കൃഷിചെയ്യുന്നു.",
    "ഉപയോഗങ്ങൾ": [
      "ഇലകൾ",
      "പുറംതൊലി",
      "വിത്തുകൾ",
      "എണ്ണ"
    ],
    "പ്രയോജനങ്ങൾ": [
      "ആൻറിമൈക്രോബയൽ",
      "ആൻറി-ഇൻഫ്ലമേറ്ററി",
      "കീടനാശിനി ഗുണങ്ങൾ"
    ],
    "പാർശ്വഫലങ്ങൾ": [
      "ദഹനനാളത്തിൻ്റെ അസ്വസ്ഥത",
      "അലർജി"
    ],
    "സുരക്ഷ മുന്നറിയിപ്പുകൾ": "വേപ്പ് ജാഗ്രതയോടെ ഉപയോഗിക്കണം, പ്രത്യേകിച്ച് ഗർഭിണികളും മുലയൂട്ടുന്ന സ്ത്രീകളും കരൾ തകരാറുള്ള വ്യക്തികളും.",
    "മരുന്ന് അലർജികൾ": "വേപ്പുമായി ബന്ധപ്പെട്ട പ്രത്യേക അലർജികൾ ഒന്നുമില്ല"
  },
  "യൂക്കാലിപ്റ്റസ്": {
    "നാമം": "യൂക്കാലിപ്റ്റസ്",
    "ജൈവ നാമം": "യൂക്കാലിപ്റ്റസ് സ്പ്",
    "വിവരണം": "മൈര്ട്ടഷ്യ കുടുംബത്തിലെ പൂച്ചെടികളുടെയും കുറ്റിച്ചെടികളുടെയും ഒരു ജനുസ്സാണ് യൂക്കാലിപ്റ്റസ്. ഇത് ഓസ്‌ട്രേലിയയിൽ നിന്നുള്ളതാണ്, തടി, അവശ്യ എണ്ണകൾ, അലങ്കാര മൂല്യങ്ങൾ എന്നിവയ്ക്കായി ലോകത്തിൻ്റെ മറ്റ് ഭാഗങ്ങളിൽ ഇത് വ്യാപകമായി കൃഷി ചെയ്യപ്പെടുന്നു.",
    "ഉപയോഗങ്ങൾ": [
      "തടി",
      "പൾപ്പ്വുഡ്",
      "ലാൻഡ്സ്കേപ്പിംഗ്",
      "എണ്ണ ഉൽപ്പാദനം"
    ],
    "പ്രയോജനങ്ങൾ": [
      "ശ്വാസകോശ സംബന്ധമായ ലക്ഷണങ്ങൾ ഒഴിവാക്കാനും പേശിവേദന ശമിപ്പിക്കാനും"
    ],
    "പാർശ്വഫലങ്ങൾ": [
      "ചർമ്മത്തിൽ പ്രകോപനം",
      "അലർജി",
      "ശ്വാസോച്ഛ്വാസം"
    ],
    "സുരക്ഷ മുന്നറിയിപ്പുകൾ": "യൂക്കാലിപ്റ്റസ് ഓയിൽ ജാഗ്രതയോടെ ഉപയോഗിക്കണം, പ്രത്യേകിച്ച് ഗർഭിണികൾ മുലയൂട്ടുന്ന സ്ത്രീകൾ, കൊച്ചുകുട്ടികൾ, ആസ്ത്മ പോലുള്ള ശ്വാസകോശ സംബന്ധമായ അസുഖങ്ങളുള്ള വ്യക്തികൾ.",
    "മരുന്ന് അലർജികൾ": "യൂക്കാലിപ്റ്റസുമായി ബന്ധപ്പെട്ട പ്രത്യേക അലർജികൾ ഒന്നുമില്ല"
  },
  "പേരയ്ക്ക": {
    "നാമം": "പേരയ്ക്ക",
    "ജൈവ നാമം": "പ്സിടിയം ഗ്വാജവ",
    "വിവരണം": "മിർട്ടഷ്യ കുടുംബത്തിൽ പെടുന്ന ഉഷ്ണമേഖലാ ഫലം കായ്ക്കുന്ന വൃക്ഷമാണ് പേരക്ക. മധ്യ അമേരിക്കയിലെ പ്രദേശങ്ങളിൽ നിന്നുള്ളതാണ് ഇത്, ലോകമെമ്പാടുമുള്ള നിരവധി ഉഷ്ണമേഖലാ പ്രദേശങ്ങളിലും ഇത് കൃഷി ചെയ്യുന്നു.",
    "ഉപയോഗങ്ങൾ": [
      "പേരയ്ക്ക പഴമായി കഴിക്കാം അല്ലെങ്കിൽ ജ്യൂസുകൾ",
      "ജാം",
      "മധുരപലഹാരങ്ങൾ"
    ],
    "പ്രയോജനങ്ങൾ": [
      "വിറ്റാമിൻ സി, വിറ്റാമിൻ എ, പൊട്ടാസ്യം, ഡയറ്ററി ഫൈബർ എന്നിവയുടെ നല്ല ഉറവിടമാണിത്."
    ],
    "പാർശ്വഫലങ്ങൾ": [
      "പഴം ലാറ്റക്സ് പ്രോട്ടീനുകളുമായി ക്രോസ്-റിയാക്റ്റ് ചെയ്യാം"
    ],
    "സുരക്ഷ മുന്നറിയിപ്പുകൾ": "ലാറ്റക്‌സ് അലർജിയുള്ള വ്യക്തികൾ പേരക്ക കഴിക്കുമ്പോൾ ജാഗ്രത പാലിക്കണം.",
    "മരുന്ന് അലർജികൾ": "പേരക്കയുടെ ഉപയോഗത്തിൽ ബന്ധപ്പെട്ട പ്രത്യേക അലർജികൾ ഒന്നുമില്ല"
  },
  "മൈലാഞ്ചി": {
    "നാമം": "മൈലാഞ്ചി",
    "ജൈവ നാമം": "ലോസോണിയ ഇനെർമിസ്",
    "വിവരണം": "ലിത്രാസി കുടുംബത്തിൽ പെട്ട ഒരു പൂവിടുന്ന സസ്യമാണ് മൈലാഞ്ചി. ആഫ്രിക്ക, ഏഷ്യ, മിഡിൽ ഈസ്റ്റ് എന്നീ പ്രദേശങ്ങളിൽ നിന്നുള്ളതാണ് മൈലാഞ്ചി.",
    "ഉപയോഗങ്ങൾ": [
      "താത്കാലിക ബോഡി ആർട്ട് (മെഹന്ദി)",
      "മുടിക്ക് നിറം നൽകൽ",
      "പ്രകൃതിദത്തമായ സൗന്ദര്യവർദ്ധക വസ്തുക്കൾ"
    ],
    "പ്രയോജനങ്ങൾ": [
      "ഹെന്നയ്ക്ക് തണുപ്പിക്കൽ",
      "ആൻ്റിമൈക്രോബയൽ ഗുണങ്ങൾ ഉണ്ട്"
    ],
    "പാർശ്വഫലങ്ങൾ": [
      "ചുവപ്പിയിലെത്തിയപ്പോൾ അലർജി ഉണ്ടാകാം"
    ],
    "സുരക്ഷ മുന്നറിയിപ്പുകൾ": "മെഹന്തി അല്ലെങ്കിൽ ഹെയർ കളറിങ്ങിനായി മൈലാഞ്ചി ഉപയോഗിക്കുന്നതിന് മുമ്പ് അലർജി പരിശോധിക്കാൻ ഒരു പാച്ച് ടെസ്റ്റ് നടത്തുക.",
    "മരുന്ന് അലർജികൾ": "മൈലാഞ്ചിയുമായി ബന്ധപ്പെട്ട പ്രത്യേക മരുന്നുകൾ അലർജികൾ ഒന്നുമില്ല"
  },
  "ചെമ്പരത്തി": {
    "നാമം": "ചെമ്പരത്തി",
    "ജൈവ നാമം": "ഹിബിസ്ക്കസ് റോസ-സിനേസിസ്",
    "വിവരണം": "മൽവഷ്യ കുടുംബത്തിലെ പൂച്ചെടികളുടെ ഒരു ജനുസ്സാണ് ചെമ്പരത്തി. ലോകമെമ്പാടുമുള്ള ഉഷ്ണമേഖലാ പ്രദേശങ്ങളിൽ നിന്നുള്ള നൂറുകണക്കിന് സ്പീഷീസുകൾ ഇതിൽ ഉൾപ്പെടുന്നു.",
    "ഉപയോഗങ്ങൾ": [
      "ഹെർബൽ ടീ",
      "പാനീയങ്ങൾ",
      "ജാം",
      "ജെല്ലി",
      "സിറപ്പുകൾ"
    ],
    "പ്രയോജനങ്ങൾ": [
      "വിറ്റാമിനുകൾ",
      "ധാതുകൾ",
      "ആൻ്റിഓക്‌സിഡൻ്റുകൾ"
    ],
    "പാർശ്വഫലങ്ങൾ": [
      "ചില വ്യക്തികളിൽ ചെമ്പരത്തി ചായയുടെ അമിത ഉപയോഗം ദഹനസംബന്ധമായ അസ്വസ്ഥത, അല്ലെങ്കിൽ കുറഞ്ഞ രക്തസമ്മർദ്ദം എന്നിവയ്ക്ക് കാരണമായേക്കാം."
    ],
    "സുരക്ഷ മുന്നറിയിപ്പുകൾ": "ഹൈപ്പർടെൻസിവ് മരുന്നുകളും ഡൈയൂററ്റിക്സും ഉൾപ്പെടെയുള്ള മരുന്നുകൾ ഉപയോഗിക്കുന്നവർ ഇത് ഒഴിവാക്കുക. ഗർഭിണികളും മുലയൂട്ടുന്ന സ്ത്രീകളും ചെമ്പരത്തി ഉൽപ്പന്നങ്ങൾ ഉപയോഗിക്കുന്നതിന് മുമ്പ് ഒരു ആരോഗ്യ വിദഗ്ധനെ സമീപിക്കേണ്ടതാണ്.",
    "മരുന്ന് അലർജികൾ": "ഹൈപ്പർടെൻസിവ് മരുന്നുകളും ഡൈയൂററ്റിക്സും ഉൾപ്പെടെയുള്ള മരുന്നുകൾ ഉപയോഗിക്കുന്നവർ ഇത് ഒഴിവാക്കുക."
  },
  "നാരങ്ങ": {
    "നാമം": "നാരങ്ങ",
    "ജൈവ നാമം": "സിട്രസ് ലിമോൺ",
    "വിവരണം": "റുട്ടേസി കുടുംബത്തിൽ പെടുന്ന ഒരു ചെറിയ നിത്യഹരിത വൃക്ഷമാണ് നാരങ്ങ. ഇതിൻ്റെ ജന്മദേശം ദക്ഷിണേഷ്യയാണെങ്കിലും അതിൻ്റെ ഫലത്തിനായി ലോകമെമ്പാടും കൃഷിചെയ്യുന്നു.",
    "ഉപയോഗങ്ങൾ": [
      "പാചക വിഭവങ്ങൾ",
      "പാനീയങ്ങൾ",
      "മധുരപലഹാരങ്ങൾ"
    ],
    "പ്രയോജനങ്ങൾ": [
      "വിറ്റാമിൻ സി",
      "സിട്രിക് ആസിഡ്",
      "ആൻ്റിഓക്‌സിഡൻ്റുകൾ"
    ],
    "പാർശ്വഫലങ്ങൾ": [
      "അമിതമായി നാരങ്ങാനീര് കഴിക്കുന്നത് അതിൻ്റെ അസിഡിറ്റി കാരണം പല്ലിൻ്റെ തേയ്മാനത്തിനോ വായിലും തൊണ്ടയിലും പ്രകോപിപ്പിക്കലിനും കാരണമായേക്കാം."
    ],
    "സുരക്ഷ മുന്നറിയിപ്പുകൾ": "രക്തം നേർപ്പിക്കുന്നതും, നെഞ്ചെരിച്ചിൽ, ആസിഡ് റിഫ്ലക്സിനുള്ള മരുന്നുകളും ഉപയോഗിക്കുന്നവർ ഇത് ഒഴിവാക്കുക. സിട്രസ് അലർജിയുള്ള വ്യക്തികൾ നാരങ്ങ ഉൽപ്പന്നങ്ങൾ ഒഴിവാക്കണം.",
    "മരുന്ന് അലർജികൾ": "രക്തം നേർപ്പിക്കുന്നതും, നെഞ്ചെരിച്ചിൽ, ആസിഡ് റിഫ്ലക്സിനുള്ള മരുന്നുകളും ഉപയോഗിക്കുന്നവർ ഇത് ഒഴിവാക്കുക."
  },
  "മല്ലിയില": {
    "നാമം": "മല്ലിയില",
    "ജൈവ നാമം": "മല്ലി സാറ്റിവം",
    "വിവരണം": "കൊത്തമല്ലി, ചൈനീസ് ആരാണാവോ എന്നും അറിയപ്പെടുന്നു. ഇത് അപിയേസി കുടുംബത്തിൽ പെട്ട ഒരു വാർഷിക സസ്യമാണ് മല്ലിയില. ഇത് തെക്കൻ യൂറോപ്പ്, വടക്കേ ആഫ്രിക്ക, തെക്കുപടിഞ്ഞാറൻ ഏഷ്യ എന്നിവിടങ്ങളിലെ പ്രദേശങ്ങളിൽ നിന്നുള്ളതാണ്.",
    "ഉപയോഗങ്ങൾ": [
      "ലോകമെമ്പാടുമുള്ള വിവിധ പാചകരീതികളിൽ",
      "സുഗന്ധവ്യഞ്ജനമായും"
    ],
    "പ്രയോജനങ്ങൾ": [
      "വിറ്റാമിൻ സി",
      "വിറ്റാമിൻ കെ",
      "പൊട്ടാസ്യം",
      "ഡയറ്ററി ഫൈബർ"
    ],
    "പാർശ്വഫലങ്ങൾ": [
      "മല്ലിയില കഴിക്കുമ്പോൾ അലർജിയോ ദഹനസംബന്ധമായ അസ്വസ്ഥതകളോ അനുഭവപ്പെടാം."
    ],
    "സുരക്ഷ മുന്നറിയിപ്പുകൾ": "പാചക അളവിൽ ഉപയോഗിക്കുമ്പോൾ മല്ലി പൊതുവെ സുരക്ഷിതമാണ്. ഗർഭിണികളോ മുലയൂട്ടുന്ന സ്ത്രീകളോ മല്ലിയില സപ്ലിമെൻ്റുകളോ എക്സ്ട്രാക്റ്റുകളോ ഉപയോഗിക്കുന്നതിന് മുമ്പ് ഒരു ഹെൽത്ത് കെയർ പ്രൊഫഷണലുമായി ബന്ധപ്പെടണം.",
    "മരുന്ന് അലർജികൾ": "മല്ലിയുമായി ബന്ധപ്പെട്ട പ്രത്യേക മരുന്നുകൾ അലർജികൾ ഒന്നുമില്ല."
  },
  "കുരുമുളക്": {
    "നാമം": "കുരുമുളക്",
    "ജൈവ നാമം": "പൈപ്പർ നൈഗ്രം",
    "വിവരണം": "പൈപ്പർ നൈഗ്രം എന്നും അറിയപ്പെടുന്ന കുരുമുളക്, പിപേരഷ്യ കുടുംബത്തിൽ പെടുന്ന ഒരു പൂവിടുന്ന മുന്തിരിവള്ളിയാണ്. ഇത് ദക്ഷിണേഷ്യയിൽ നിന്നുള്ളതാണ്, എന്നാൽ ഇപ്പോൾ ലോകമെമ്പാടുമുള്ള ഉഷ്ണമേഖലാ പ്രദേശങ്ങളിൽ കൃഷി ചെയ്യുന്നു.",
    "ഉപയോഗങ്ങൾ": [
      "കുരുമുളക് പാചക വിഭവങ്ങൾ",
      "സോസുകൾ",
      "മാരിനേഡുകൾ"
    ],
    "പ്രയോജനങ്ങൾ": [
      "കുരുമുളകിൽ പൈപ്പറിൻ പോലെയുള്ള ബയോആക്ടീവ് സംയുക്തങ്ങൾ അടങ്ങിയിരിക്കുന്നു",
      "പോഷകങ്ങളുടെ ആഗിരണം വർദ്ധിപ്പിക്കും"
    ],
    "പാർശ്വഫലങ്ങൾ": [
      "കുരുമുളക് കഴിക്കുന്നത് ദഹനനാളത്തിൻ്റെ അസ്വസ്ഥത, നെഞ്ചെരിച്ചിൽ, അലർജി എന്നിവയ്ക്ക് കാരണമായേക്കാം."
    ],
    "സുരക്ഷ മുന്നറിയിപ്പുകൾ": "കുരുമുളക് മിതമായി കഴിക്കണം, പ്രത്യേകിച്ച് ദഹനസംബന്ധമായ പ്രശ്‌നങ്ങൾ, അൾസർ തുടങ്ങിയവ ഉള്ളവർ ജാഗ്രത പാലിക്കണം.",
    "മരുന്ന് അലർജികൾ": "കുരുമുളകുമായി ബന്ധപ്പെട്ട് പ്രത്യേക മരുന്നുകൾ അലർജികൾ ഒന്നുമില്ല."
  },
  "പുതിന": {
    "നാമം": "പുതിന",
    "ജൈവ നാമം": "മെന്ത",
    "വിവരണം": "ലാമിയേസി കുടുംബത്തിലെ സുഗന്ധമുള്ള ഔഷധസസ്യങ്ങളുടെ ഒരു ജനുസ്സാണ് പുതിന. പുതിന യുറേഷ്യയിൽ നിന്നുള്ളതാണ്, എന്നാൽ ഇപ്പോൾ ലോകമെമ്പാടും ഇത് കാണപ്പെടുന്നു.",
    "ഉപയോഗങ്ങൾ": [
      "പാചക വിഭവങ്ങൾ",
      "പാനീയങ്ങൾ",
      "ചായകൾ",
      "കോക്ക്ടെയിലുകൾ",
      "മധുരപലഹാരങ്ങൾ"
    ],
    "പ്രയോജനങ്ങൾ": [
      "പുതിനയിൽ മെന്തോൾ അടങ്ങിയിട്ടുണ്ട്",
      "പേരുകേട്ട ഒരു സംയുക്തമായാണ് പുതിന",
      "ശ്വാസം ഉത്തേജിപ്പിക്കാനും വായുടെ ആരോഗ്യം മെച്ചപ്പെടുത്താനും പുതിന ഉപയോഗിക്കുന്നു"
    ],
    "പാർശ്വഫലങ്ങൾ": [
      "ചില വ്യക്തികളിൽ, പുതിനയുടെ അമിതമായ ഉപയോഗം നെഞ്ചെരിച്ചിൽ, ആസിഡ് റിഫ്ലക്സ്, ദഹനനാള പ്രശ്നം എന്നിവയ്ക്ക് കാരണമായേക്കാം"
    ],
    "സുരക്ഷ മുന്നറിയിപ്പുകൾ": "പാചക അളവിൽ ഉപയോഗിക്കുമ്പോൾ പുതിന പൊതുവെ സുരക്ഷിതമാണ്. ഗർഭിണികളോ മുലയൂട്ടുന്ന സ്ത്രീകളോ പുതിന സപ്ലിമെൻ്റുകളോ എക്സ്ട്രാക്റ്റുകളോ ഉപയോഗിക്കുന്നതിന് മുമ്പ് ഒരു ഹെൽത്ത് കെയർ പ്രൊഫഷണലുമായി ബന്ധപ്പെടണം.",
    "മരുന്ന് അലർജികൾ": "പുതിനയുമായി ബന്ധപ്പെട്ട് പ്രത്യേക അലർജികൾ ഒന്നുമില്ല."
  },
  "പുളി": {
    "നാമം": "പുളി",
    "ജൈവ നാമം": "താമറിൻഡസ് ഇൻഡിക്ക",
    "വിവരണം": "ഫാബേസി കുടുംബത്തിൽ പെടുന്ന ഒരു ഉഷ്ണമേഖലാ വൃക്ഷമാണ് പുളി. ഇത് ആഫ്രിക്കയിൽ നിന്നുള്ളതാണ്, പക്ഷേ അതിൻ്റെ ഭക്ഷ്യയോഗ്യമായ ഫലത്തിനായി ലോകമെമ്പാടുമുള്ള ഉഷ്ണമേഖലാ പ്രദേശങ്ങളിൽ കൃഷി ചെയ്യുന്നു.",
    "ഉപയോഗങ്ങൾ": [
      "പുളി പാചക വിഭവങ്ങൾ",
      "പാനീയങ്ങൾ",
      "സോസുകൾ",
      "ചട്നികൾ",
      "മിഠായികൾ"
    ],
    "പ്രയോജനങ്ങൾ": [
      "പുളി വിറ്റാമിനുകൾ, ധാതുക്കൾ, ആൻ്റിഓക്‌സിഡൻ്റുകൾ, പ്രത്യേകിച്ച് വിറ്റാമിൻ സി, ടാർടാറിക് ആസിഡ്"
    ],
    "പാർശ്വഫലങ്ങൾ": [
      "ചില വ്യക്തികൾക്ക് പുളി കഴിച്ചതിനുശേഷം അലർജിയോ ദഹനസംബന്ധമായ അസ്വസ്ഥതകളോ അനുഭവപ്പെടാം"
    ],
    "സുരക്ഷ മുന്നറിയിപ്പുകൾ": "പുളി മിതമായ അളവിൽ കഴിയ്ക്കുമ്പോഴും ഉപയോഗിക്കുന്നതിന് പൊതുവെ സുരക്ഷിതമാണ്. പ്രമേഹമുള്ള വ്യക്തികൾ പുളിയുടെ ഉൽപന്നങ്ങളുടെ അധികമായി ഉപയോഗിക്കരുത്.",
    "മരുന്ന് അലർജികൾ": "പുളിയുമായി ബന്ധപ്പെട്ട് പ്രത്യേക അലർജികൾ ഒന്നുമില്ല."
  },
  "തുളസി": {
    "നാമം": "തുളസി",
    "ജൈവ നാമം": "സോളാനം ലൈക്കോപെർസിക്കം",
    "വിവരണം": "വിശുദ്ധ തുളസി എന്നും അറിയപ്പെടുന്ന തുളസി, ലാമിയേസി കുടുംബത്തിൽപ്പെട്ട ഒരു സുഗന്ധ സസ്യമാണ്. ഇത് ഇന്ത്യൻ ഉപഭൂഖണ്ഡത്തിൽ നിന്നുള്ളതാണ്.",
    "ഉപയോഗങ്ങൾ": [
      "ഹിന്ദുമതത്തിൽ പവിത്രമായി കണക്കാക്കുക",
      "വിവിധ മതപരമായ ചടങ്ങുകളിൽ ഉപയോഗിക്കുക"
    ],
    "പ്രയോജനങ്ങൾ": [
      "അഡാപ്റ്റോജെനിക്",
      "ആൻ്റിഓക്‌സിഡൻ്റ്",
      "ഇമ്മ്യൂണോമോഡുലേറ്ററി പ്രോപ്പർട്ടികൾ"
    ],
    "പാർശ്വഫലങ്ങൾ": [
      "ചില വ്യക്തികൾക്ക് ഓക്കാനം, തലകറക്കം അല്ലെങ്കിൽ അലർജി പോലുള്ള നേരിയ പാർശ്വഫലങ്ങൾ അനുഭവപ്പെടാം."
    ],
    "സുരക്ഷ മുന്നറിയിപ്പുകൾ": "ഗർഭിണികളും മുലയൂട്ടുന്ന സ്ത്രീകളും രക്തസ്രാവ വൈകല്യമുള്ള വ്യക്തികളും തുളസി ജാഗ്രതയോടെ ഉപയോഗിക്കണം.",
    "മരുന്ന് അലർജികൾ": "തുളസിയുമായി ബന്ധപ്പെട്ട് പ്രത്യേക അലർജികൾ ഒന്നുമില്ല."
  },
  "മഞ്ഞൾ": {
    "നാമം": "മഞ്ഞൾ",
    "ജൈവ നാമം": "കുർകുമാ ലോംഗ",
    "വിവരണം": "മകുർകുമാ ലോംഗ എന്നും അറിയപ്പെടുന്ന മഞ്ഞൾ, ഇഞ്ചി കുടുംബമായ സിംഗിബെറേസിയിൽപെടുന്ന ഒരു പൂച്ചെടിയാണ്. ഇത് ദക്ഷിണേഷ്യയിൽ നിന്നുള്ളതാണ്, എന്നാൽ ഇപ്പോൾ ലോകമെമ്പാടുമുള്ള ഉഷ്ണമേഖലാ പ്രദേശങ്ങളിലും കൃഷി ചെയ്യുന്നു.",
    "ഉപയോഗങ്ങൾ": [
      "പാചകത്തിൽ സുഗന്ധവ്യഞ്ജനമായും",
      "പാനീയങ്ങൾ",
      "ചായകൾ",
      "പരമ്പരാഗത വൈദ്യശാസ്ത്രം"
    ],
    "പ്രയോജനങ്ങൾ": [
      "ആൻ്റി-ഇൻഫ്ലമേറ്ററി",
      "ആൻ്റിഓക്‌സിഡൻ്റ്",
      "ആൻറി കാൻസർ ഇഫക്റ്റുകൾ"
    ],
    "പാർശ്വഫലങ്ങൾ": [
      "ദഹനനാളത്തിൻ്റെ അസ്വസ്ഥത",
      "ഓക്കാനം",
      "അലർജി"
    ],
    "സുരക്ഷ മുന്നറിയിപ്പുകൾ": "മഞ്ഞളിൽ കുർക്കുമിൻ മിതമായ അളവിൽ കഴിക്കണം, ദഹനസംബന്ധമായ പ്രശ്നങ്ങൾ, പിത്തസഞ്ചി പ്രശ്നങ്ങൾ എന്നിവയുള്ള വ്യക്തികൾ. ഗർഭിണികൾ വലിയ അളവിൽ മഞ്ഞൾ കഴിക്കുന്നതിന് മുമ്പ് ഒരു ആരോഗ്യ വിദഗ്ദ്ധനെ സമീപിക്കേണ്ടതാണ്.",
    "മരുന്ന് അലർജികൾ": "മഞ്ഞളുമായി ബന്ധപ്പെട്ട് പ്രത്യേക അലർജികൾ ഒന്നുമില്ല."
  },
  "മുള": {
    "നാമം": "മുള",
    "ജൈവ നാമം": "ബാംബുസോയ്ഡേ",
    "വിവരണം": "പോയേസി കുടുംബത്തിൽ പെട്ട അതിവേഗം വളരുന്ന സസ്യങ്ങളുടെ ഒരു കൂട്ടമാണ് മുള. ഏഷ്യ, ആഫ്രിക്ക, അമേരിക്ക എന്നിവിടങ്ങളിലെ വിവിധ പ്രദേശങ്ങളിൽ നിന്നുള്ളതാണ് മുള.",
    "ഉപയോഗങ്ങൾ": [
      "പാചക വിഭവങ്ങൾ",
      "പാനീയങ്ങൾ",
      "ചായകൾ",
      "പരമ്പരാഗത വൈദ്യശാസ്ത്രം"
    ],
    "പ്രയോജനങ്ങൾ": [
      "സിലിക്ക",
      "ആൻ്റിഓക്‌സിഡൻ്റുകൾ",
      "ഫ്ലേവനോയ്ഡുകൾ"
    ],
    "പാർശ്വഫലങ്ങൾ": [
      "ദഹനനാളത്തിൻ്റെ അസ്വസ്ഥത",
      "അലർജി"
    ],
    "സുരക്ഷ മുന്നറിയിപ്പുകൾ": "പ്രകൃതിദത്തമായ വിഷാംശങ്ങളും പോഷക വിരുദ്ധ ഘടകങ്ങളും നീക്കം ചെയ്യുന്നതിനായി മുളകൾ കഴിക്കുന്നതിന് മുമ്പ് നന്നായി പാകം ചെയ്യണം. പുല്ലുകളോട് അലർജിയോ ചില ഭക്ഷണങ്ങളോട് സംവേദനക്ഷമതയോ ഉള്ള വ്യക്തികൾ മുള ഉൽപ്പന്നങ്ങൾ കഴിക്കുമ്പോൾ ജാഗ്രത പാലിക്കണം.",
    "മരുന്ന് അലർജികൾ": "മുളയുമായി ബന്ധപ്പെട്ട് പ്രത്യേക മരുന്നുകൾ അലർജികൾ ഒന്നുമില്ല."
  },
  "പപ്പായ": {
    "നാമം": "പപ്പായ",
    "ജൈവ നാമം": "കാരിക്ക പപ്പായ",
    "വിവരണം": "പപ്പായ അല്ലെങ്കിൽ കാരിക്ക പപ്പായ എന്നും അറിയപ്പെടുന്ന പപ്പായ, കാരിക്കേസി കുടുംബത്തിൽ പെടുന്ന ഒരു ഉഷ്ണമേഖലാ ഫലവൃക്ഷമാണ്.",
    "ഉപയോഗങ്ങൾ": [
      "പപ്പായ പഴം",
      "ഇലകൾ",
      "വിത്തുകൾ",
      "ലാറ്റക്സ്"
    ],
    "പ്രയോജനങ്ങൾ": [
      "വിറ്റാമിനുകൾ",
      "ധാതുകൾ",
      "ആൻ്റിഓക്‌സിഡൻ്റുകൾ",
      "എൻസൈമുകൾ"
    ],
    "പാർശ്വഫലങ്ങൾ": [
      "അലർജി",
      "ദഹനസംബന്ധമായ അസ്വസ്ഥതകൾ"
    ],
    "സുരക്ഷ മുന്നറിയിപ്പുകൾ": "ലാറ്റക്‌സിനോ ചെടികൾക്കോ അലർജിയുള്ള വ്യക്തികൾ പപ്പായ ലാറ്റക്സ് ചർമ്മത്തെ പ്രകോപിപ്പിക്കുകയോ അലർജി ഉണ്ടാക്കുകയോ ചെയ്തേക്കാം.",
    "മരുന്ന് അലർജികൾ": "പപ്പായയുമായി ബന്ധപ്പെട്ട് പ്രത്യേക മരുന്നു അലർജികൾ ഒന്നുമില്ല."
  },
  "മുളക്": {
    "നാമം": "മുളക്",
    "ജൈവ നാമം": "കാപ്സിക്കം അന്നും",
    "വിവരണം": "മുളക്, സോളനേസിയേ എന്ന നൈറ്റ്ഷെയ്ഡ് കുടുംബത്തിലെ അംഗമാണ്. ഇത് മധ്യ, തെക്കേ അമേരിക്കയിൽ നിന്നുള്ളതാണ്.",
    "ഉപയോഗങ്ങൾ": [
      "ഉണക്കിയതോ പൊടിച്ചതോ സോസുകളിലേക്കും സുഗന്ധവ്യഞ്ജനങ്ങളിലേക്കും ഉപയോഗിക്കുന്നു"
    ],
    "പ്രയോജനങ്ങൾ": [
      "വിറ്റാമിനുകൾ",
      "ധാതുകൾ",
      "ആൻ്റിഓക്‌സിഡൻ്റുകൾ",
      "ക്യാപ്‌സൈസിനോയിഡുകൾ"
    ],
    "പാർശ്വഫലങ്ങൾ": [
      "ദഹനനാളത്തിൻ്റെ അസ്വസ്ഥത",
      "നെഞ്ചെരിച്ചിൽ",
      "ദഹനനാളത്തിൻ്റെ പ്രകോപനം"
    ],
    "സുരക്ഷ മുന്നറിയിപ്പുകൾ": "ആസിഡ് റിഫ്ലക്സ് അല്ലെങ്കിൽ ഇറിറ്റബിൾ ബവൽ സിൻഡ്രോം പോലുള്ള ഗ്യാസ്ട്രോഇൻ്റസ്റ്റൈനൽ ഡിസോർഡേഴ്സ് ഉള്ള വ്യക്തികൾ മുളകുപൊടി മിതമായ അളവിൽ കഴിക്കണം.",
    "മരുന്ന് അലർജികൾ": "മുളകുമായി ബന്ധപ്പെട്ട് പ്രത്യേക മരുന്നു അലർജികൾ ഒന്നുമില്ല."
  },
  "മുരിങ്ങ": {
    "നാമം": "മുരിങ്ങ",
    "ജൈവ നാമം": "മൊറിംഗ ഒലിഫെറ",
    "വിവരണം": "മുരിങ്ങ, ദക്ഷിണേഷ്യയിലെ ഉഷ്ണമേഖല പ്രദേശങ്ങളിൽ നിന്നുള്ള അതിവേഗം വളരുന്ന ഒരു വൃക്ഷമാണ്.",
    "ഉപയോഗങ്ങൾ": [
      "ഇലകൾ",
      "പഴങ്ങൾ",
      "വിത്തുകൾ",
      "വേരുകൾ"
    ],
    "പ്രയോജനങ്ങൾ": [
      "വിറ്റാമിനുകൾ",
      "ധാതുകൾ",
      "ആൻ്റിഓക്‌സിഡൻ്റുകൾ",
      "പ്രോട്ടീൻ"
    ],
    "പാർശ്വഫലങ്ങൾ": [
      "ദഹനസംബന്ധമായ അസ്വസ്ഥത"
    ],
    "സുരക്ഷ മുന്നറിയിപ്പുകൾ": "ഹൈപ്പോടെൻഷൻ അല്ലെങ്കിൽ കിഡ്നി ഡിസോർഡേഴ്സ് പോലുള്ള രോഗാവസ്ഥകളുള്ള വ്യക്തികൾ മുരിങ്ങയില കഴിക്കുമ്പോൾ ജാഗ്രത പാലിക്കണം.",
    "മരുന്ന് അലർജികൾ": "മുരിങ്ങയിലയുമായി ബന്ധപ്പെട്ട് പ്രത്യേക അലർജികൾ ഒന്നുമില്ല."
  },
  "ചക്ക": {
    "നാമം": "ചക്ക",
    "ജൈവ നാമം": "ആർട്ടോകാർപസ് ഹെറ്ററോഫില്ലസ്",
    "വിവരണം": "മൊറേസി കുടുംബത്തിൽ പെട്ട ഉഷ്ണമേഖലാ വൃക്ഷമാണ് ചക്ക. തെക്ക്, തെക്കുകിഴക്കൻ ഏഷ്യ എന്നിവിടങ്ങളിൽ നിന്നുള്ളതാണ് ചക്ക.",
    "ഉപയോഗങ്ങൾ": [
      "ചക്ക പഴം",
      "മധുരപലഹാരങ്ങൾ",
      "കറികൾ",
      "പായസങ്ങൾ",
      "ലഘുഭക്ഷണങ്ങൾ"
    ],
    "പ്രയോജനങ്ങൾ": [
      "വിറ്റാമിനുകൾ",
      "ധാതുകൾ",
      "ആൻ്റിഓക്‌സിഡൻ്റുകൾ",
      "വിറ്റാമിൻ സി",
      "പൊട്ടാസ്യം"
    ],
    "പാർശ്വഫലങ്ങൾ": [
      "അലർജി"
    ],
    "സുരക്ഷ മുന്നറിയിപ്പുകൾ": "ചക്ക മിതമായ അളവിൽ കഴിക്കുമ്പോ പൊതുവെ സുരക്ഷിതമാണ്.",
    "മരുന്ന് അലർജികൾ": "ചക്കയുമായി ബന്ധപ്പെട്ട പ്രത്യേക അലർജികൾ ഒന്നുമില്ല."
  },
  "ജാസ്മിൻ": {
    "നാമം": "ജാസ്മിൻ",
    "ജൈവ നാമം": "ജാസ്മിനം എസ്പിപി",
    "വിവരണം": "ഒലിയേസീ കുടുംബത്തിലെ പൂച്ചെടികളുടെ ഒരു ജനുസ്സാണ് ജാസ്മിൻ. യുറേഷ്യ, ഓസ്‌ട്രലേഷ്യ, ഓഷ്യാനിയ എന്നിവിടങ്ങളിലെ ഉഷ്ണമേഖലാ, ഉപ ഉഷ്ണമേഖലാ പ്രദേശങ്ങളിൽ നിന്നുള്ള വൈവിധ്യമാർന്ന സ്പീഷിസുകൾ ഇതിൽ ഉൾപ്പെടുന്നു.",
    "ഉപയോഗങ്ങൾ": [
      "മുല്ലപ്പൂക്കൾ",
      "സുഗന്ധദ്രവ്യങ്ങൾ",
      "മതപരമായ ചടങ്ങുകൾ"
    ],
    "പ്രയോജനങ്ങൾ": [
      "സമ്മർദ്ദം",
      "ഉത്കണ്ഠ",
      "വിഷാദം",
      "ഉറക്കം"
    ],
    "പാർശ്വഫലങ്ങൾ": [
      "അലർജി"
    ],
    "സുരക്ഷ മുന്നറിയിപ്പുകൾ": "ജാസ്മിൻ എണ്ണ ജാഗ്രതയോടെ ഉപയോഗിക്കണം, കാരണം അത് ശക്തിയുള്ളതും ചർമ്മത്തിൽ പ്രകോപിപ്പിക്കലിനോ സെൻസിറ്റൈസേഷനോ കാരണമാകും.",
    "മരുന്ന് അലർജികൾ": "മുല്ലപ്പൂവുമായി ബന്ധപ്പെട്ട പ്രത്യേക മരുന്നുകൾ അലർജികൾ ഒന്നുമില്ല."
  },
  "മാമ്പഴം": {
    "നാമം": "മാമ്പഴം",
    "ജൈവ നാമം": "മഗ്നിഫെറ ഇൻഡിക്ക",
    "വിവരണം": "അനാകാർഡിയേസി കുടുംബത്തിൽപ്പെട്ട ഉഷ്ണമേഖലാ ഫലം കായ്ക്കുന്ന വൃക്ഷമാണ് മാമ്പഴം. ഇത് ദക്ഷിണേഷ്യയിൽ നിന്നുള്ളതാണ്, പക്ഷേ ഭക്ഷ്യയോഗ്യമായ പഴങ്ങൾക്കായി ലോകമെമ്പാടുമുള്ള ഉഷ്ണമേഖലാ പ്രദേശങ്ങളിലും ഉപ ഉഷ്ണമേഖലാ പ്രദേശങ്ങളിലും കൃഷി ചെയ്യുന്നു.",
    "ഉപയോഗങ്ങൾ": [
      "പാചക വിഭവങ്ങൾ",
      "മധുരപലഹാരങ്ങൾ",
      "സ്മൂത്തികൾ",
      "ജ്യൂസുകൾ",
      "ജാം",
      "ചട്നികൾ"
    ],
    "പ്രയോജനങ്ങൾ": [
      "വിറ്റാമിനുകൾ",
      "ധാതുക്കൾ",
      "ആൻ്റിഓക്‌സിഡൻ്റുകൾ"
    ],
    "പാർശ്വഫലങ്ങൾ": [
      "അലർജി",
      "കോൺടാക്റ്റ് ഡെർമറ്റൈറ്റിസ്"
    ],
    "സുരക്ഷ മുന്നറിയിപ്പുകൾ": "മാമ്പഴം പഴുക്കുമ്പോഴും മിതമായ അളവിൽ കഴിക്കുന്നത് പൊതുവെ സുരക്ഷിതമാണ്.",
    "മരുന്ന് അലർജികൾ": "മാമ്പഴവുമായി ബന്ധപ്പെട്ട പ്രത്യേക മരുന്നുകൾ അലർജികൾ ഒന്നുമില്ല."
  },
  "റോസ്": {
    "നാമം": "റോസ്",
    "ജൈവ നാമം": "റോസ എസ്പിപി",
    "വിവരണം": "റോസാസി കുടുംബത്തിലെ റോസ് ജനുസ്സിൽ പെട്ട ഒരു മരം നിറയെ പൂക്കളുള്ള ചെടിയാണ് റോസ്. സുഗന്ധമുള്ള പൂക്കൾക്ക് വേണ്ടിയാണ് ഇത് കൃഷി ചെയ്യുന്നത്, നൂറ്റാണ്ടുകളായി അവയുടെ സൌന്ദര്യത്തിനും സുഗന്ധത്തിനും വിലമതിക്കപ്പെടുന്നു.",
    "ഉപയോഗങ്ങൾ": [
      "റോസാപ്പൂക്കൾ",
      "സുഗന്ധദ്രവ്യങ്ങൾ",
      "പാചക പ്രയോഗങ്ങൾ"
    ],
    "പ്രയോജനങ്ങൾ": [
      "വിറ്റാമിനുകൾ",
      "ആൻ്റിഓക്‌സിഡൻ്റുകൾ",
      "ചർമ്മത്തിന്റെ ആരോഗ്യം"
    ],
    "പാർശ്വഫലങ്ങൾ": [
      "അലർജി"
    ],
    "സുരക്ഷ മുന്നറിയിപ്പുകൾ": "മിതമായ അളവിൽ ഉപയോഗിക്കുമ്പോൾ റോസ് മിക്കവർക്കും സുരക്ഷിതമാണ്.",
    "മരുന്ന് അലർജികൾ": "റോസാപ്പൂക്കളുമായി ബന്ധപ്പെട്ട പ്രത്യേക മരുന്നുകൾ അലർജികൾ ഒന്നുമില്ല."
  },
  "തക്കാളി": {
    "നാമം": "തക്കാളി",
    "ജൈവ നാമം": "സോളാനം ലൈക്കോപെർസിക്കം",
    "വിവരണം": "സോളനേസിയേ കുടുംബത്തിൽ പെടുന്ന ഒരു പൂച്ചെടിയാണ് തക്കാളി. പടിഞ്ഞാറൻ തെക്കേ അമേരിക്കയിൽ നിന്നുള്ളതാണ് തക്കാളി, എന്നാൽ ഇപ്പോൾ ലോകമെമ്പാടും അതിൻ്റെ ഭക്ഷ്യയോഗ്യമായ പഴങ്ങൾക്കായി കൃഷി ചെയ്യുന്നു.",
    "ഉപയോഗങ്ങൾ": [
      "പാചക വിഭവങ്ങൾ",
      "സലാഡുകൾ",
      "സൂപ്പ്",
      "സോസുകൾ",
      "പലവ്യഞ്ജനങ്ങൾ"
    ],
    "പ്രയോജനങ്ങൾ": [
      "വിറ്റാമിനുകൾ",
      "ധാതുകൾ",
      "ആൻ്റിഓക്‌സിഡൻ്റുകൾ",
      "ലൈക്കോപീൻ ഉൾപ്പെടെയുള്ള ഫൈറ്റോകെമിക്കലുകൾ"
    ],
    "പാർശ്വഫലങ്ങൾ": [
      "അലർജി"
    ],
    "സുരക്ഷ മുന്നറിയിപ്പുകൾ": "മിതമായ അളവിൽ ഉപയോഗിക്കുമ്പോൾ സുരക്ഷിതമാണ്.",
    "മരുന്ന് അലർജികൾ": "തക്കാളിയുമായി ബന്ധപ്പെട്ട പ്രത്യേക മരുന്നുകൾ അലർജികൾ ഒന്നുമില്ല."
  }
}